collective.themesitesetup-2.1.2-py2.7-nspkg.pth
collective/themesitesetup/__init__.py
collective/themesitesetup/browser.py
collective/themesitesetup/configure.zcml
collective/themesitesetup/content.py
collective/themesitesetup/extras.zcml
collective/themesitesetup/interfaces.py
collective/themesitesetup/marshall.py
collective/themesitesetup/plugin.py
collective/themesitesetup/testing.py
collective/themesitesetup/utils.py
collective/themesitesetup/tests/__init__.py
collective/themesitesetup/tests/configure.zcml
collective/themesitesetup/tests/my-theme.zip
collective/themesitesetup/tests/test_disabled.robot
collective/themesitesetup/tests/test_enabled.robot
collective/themesitesetup/tests/test_export.robot
collective/themesitesetup/tests/test_import.robot
collective/themesitesetup/tests/test_robot.py
collective.themesitesetup-2.1.2.dist-info/DESCRIPTION.rst
collective.themesitesetup-2.1.2.dist-info/METADATA
collective.themesitesetup-2.1.2.dist-info/RECORD
collective.themesitesetup-2.1.2.dist-info/WHEEL
collective.themesitesetup-2.1.2.dist-info/entry_points.txt
collective.themesitesetup-2.1.2.dist-info/metadata.json
collective.themesitesetup-2.1.2.dist-info/namespace_packages.txt
collective.themesitesetup-2.1.2.dist-info/top_level.txt
