Metadata-Version: 2.0
Name: collective.themesitesetup
Version: 2.1.2
Summary: GenericSetup profiles for plone.app.theming
Home-page: https://github.com/collective/collective.themesitesetup/
Author: Asko Soukka
Author-email: asko.soukka@iki.fi
License: GPL
Platform: UNKNOWN
Classifier: Programming Language :: Python
Classifier: Framework :: Plone :: 4.1
Classifier: Framework :: Plone :: 4.2
Classifier: Framework :: Plone :: 4.3
Requires-Dist: collective.monkeypatcher
Requires-Dist: plone.api
Requires-Dist: plone.app.controlpanel
Requires-Dist: plone.app.theming
Requires-Dist: plone.autoform
Requires-Dist: plone.dexterity
Requires-Dist: plone.supermodel
Requires-Dist: plone.z3cform
Requires-Dist: polib
Requires-Dist: Products.GenericSetup
Requires-Dist: setuptools
Requires-Dist: z3c.form
Requires-Dist: zope.app.i18n (<4.0.0)
Requires-Dist: zope.app.localpermission
Requires-Dist: zope.event
Requires-Dist: zope.globalrequest
Requires-Dist: zope.i18n
Requires-Dist: zope.lifecycleevent
Requires-Dist: zope.schema
Provides-Extra: test
Requires-Dist: plone.app.testing; extra == 'test'
Requires-Dist: plone.app.robotframework; extra == 'test'
Requires-Dist: robotframework-selenium2screenshots; extra == 'test'
